
[
  {
    "photo": "Green Hill.png"
  },
  {
    "photo": "Hotel Hill.png"
  },
  {
    "photo": "Road.png"
  },
  {
    "photo": "3D cube images.webp"
  },
  {
    "photo": "3D flower.webp"
  },
  {
    "photo": "3D wave board.webp"
  },
  {
    "photo": "Above ocean.webp"
  },
  {
    "photo": "New Aesthetic.webp"
  },
  {
    "photo": "Aesthetic.webp"
  },
  {
    "photo": "Alone.webp"
  },
  {
    "photo": "Alowera.webp"
  },
  {
    "photo": "Apple.webp"
  },
  {
    "photo": "Architect.webp"
  },
  {
    "photo": "Architecture.webp"
  },
  {
    "photo": "Aunthum view.webp"
  },
  {
    "photo": "Austarlia.webp"
  },
  {
    "photo": "Authem.webp"
  },
  {
    "photo": "Autumn poems.webp"
  },
  {
    "photo": "Bali.webp"
  },
  {
    "photo": "Banff.webp"
  },
  {
    "photo": "Beach background.webp"
  },
  {
    "photo": "Beach bungalow.webp"
  },
  {
    "photo": "Beach hillside.webp"
  },
  {
    "photo": "Beach nature.webp"
  },
  {
    "photo": "Beach sun.webp"
  },
  {
    "photo": "Beach swiming.webp"
  },
  {
    "photo": "Beach waves.webp"
  },
  {
    "photo": "Beautiful river.webp"
  },
  {
    "photo": "Bicycle.webp"
  },
  {
    "photo": "Black red street.webp"
  },
  {
    "photo": "Black sky stars.webp"
  },
  {
    "photo": "Black wallpaper.webp"
  },
  {
    "photo": "Blue beach hotel.webp"
  },
  {
    "photo": "Blue door.webp"
  },
  {
    "photo": "Blue flowers.webp"
  },
  {
    "photo": "Blue ocean.webp"
  },
  {
    "photo": "Blue tower.webp"
  },
  {
    "photo": "Blue wooden.webp"
  },
  {
    "photo": "Blue yellow abstract.webp"
  },
  {
    "photo": "Blue-pink neon.webp"
  },
  {
    "photo": "Blure.webp"
  },
  {
    "photo": "Boat river.webp"
  },
  {
    "photo": "Boating.webp"
  },
  {
    "photo": "Boatman.webp"
  },
  {
    "photo": "Brazil.webp"
  },
  {
    "photo": "Bridge.webp"
  },
  {
    "photo": "Britain.webp"
  },
  {
    "photo": "Build home.webp"
  },
  {
    "photo": "Building stairs.webp"
  },
  {
    "photo": "Bulb.webp"
  },
  {
    "photo": "Bulding background.webp"
  },
  {
    "photo": "Bungalow top view.webp"
  },
  {
    "photo": "Butterfly.webp"
  },
  {
    "photo": "Capital city with beach.webp"
  },
  {
    "photo": "Cathedral.webp"
  },
  {
    "photo": "Cave in mexico.webp"
  },
  {
    "photo": "Center view.webp"
  },
  {
    "photo": "Cheras.webp"
  },
  {
    "photo": "City center mall.webp"
  },
  {
    "photo": "City chowk.webp"
  },
  {
    "photo": "City street view.webp"
  },
  {
    "photo": "Citylights.webp"
  },
  {
    "photo": "Clock tower.webp"
  },
  {
    "photo": "Clothes.webp"
  },
  {
    "photo": "Clouds.webp"
  },
  {
    "photo": "Coffee hotel.webp"
  },
  {
    "photo": "Coffee tea.webp"
  },
  {
    "photo": "Coffee with mug.webp"
  },
  {
    "photo": "Contraction.webp"
  },
  {
    "photo": "Cookies.webp"
  },
  {
    "photo": "Cool beach.webp"
  },
  {
    "photo": "Countryside.webp"
  },
  {
    "photo": "Couple love.webp"
  },
  {
    "photo": "Craft.webp"
  },
  {
    "photo": "Creater.webp"
  },
  {
    "photo": "Cruise boat.webp"
  },
  {
    "photo": "Cube corner.webp"
  },
  {
    "photo": "Current.webp"
  },
  {
    "photo": "Cute cat.webp"
  },
  {
    "photo": "Cute.webp"
  },
  {
    "photo": "Cutey.webp"
  },
  {
    "photo": "Dark hill river.webp"
  },
  {
    "photo": "Dark hill.webp"
  },
  {
    "photo": "Dark sky pink.webp"
  },
  {
    "photo": "Daylighting.webp"
  },
  {
    "photo": "Delhi mahel.webp"
  },
  {
    "photo": "Desert camp.webp"
  },
  {
    "photo": "Desert.webp"
  },
  {
    "photo": "Dog animal.webp"
  },
  {
    "photo": "Dog images.webp"
  },
  {
    "photo": "Dreamer.webp"
  },
  {
    "photo": "Drop.webp"
  },
  {
    "photo": "Dubai.webp"
  },
  {
    "photo": "Eiffel tower abstract.webp"
  },
  {
    "photo": "Elivation.webp"
  },
  {
    "photo": "Embassy here feat.webp"
  },
  {
    "photo": "England.webp"
  },
  {
    "photo": "Fantastic waterfall.webp"
  },
  {
    "photo": "Festival.webp"
  },
  {
    "photo": "Festivity.webp"
  },
  {
    "photo": "Feuerwerk.webp"
  },
  {
    "photo": "Fire hand.webp"
  },
  {
    "photo": "Flamingo sea.webp"
  },
  {
    "photo": "Flower pot.webp"
  },
  {
    "photo": "Flower view.webp"
  },
  {
    "photo": "Flowers.webp"
  },
  {
    "photo": "Foggy city weather.webp"
  },
  {
    "photo": "Forest 3d.webp"
  },
  {
    "photo": "Forest morning.webp"
  },
  {
    "photo": "Forest rain.webp"
  },
  {
    "photo": "Forest river green.webp"
  },
  {
    "photo": "Full hd bulding background.webp"
  },
  {
    "photo": "Full hd dog.webp"
  },
  {
    "photo": "Full hd river.webp"
  },
  {
    "photo": "Funny cat pictures.webp"
  },
  {
    "photo": "Galaxy sky.webp"
  },
  {
    "photo": "Gelexy pic.webp"
  },
  {
    "photo": "Goa.webp"
  },
  {
    "photo": "Green city.webp"
  },
  {
    "photo": "Green hill city.webp"
  },
  {
    "photo": "Green hill zone.webp"
  },
  {
    "photo": "Green hills.webp"
  },
  {
    "photo": "Green neon.webp"
  },
  {
    "photo": "Green park.webp"
  },
  {
    "photo": "Green sky ten fire.webp"
  },
  {
    "photo": "Greenery.webp"
  },
  {
    "photo": "Hand flower.webp"
  },
  {
    "photo": "Hd green wallpapers.webp"
  },
  {
    "photo": "Hd tower.webp"
  },
  {
    "photo": "Heart sky.webp"
  },
  {
    "photo": "Hend paper.webp"
  },
  {
    "photo": "Hill beach.webp"
  },
  {
    "photo": "Hill center.webp"
  },
  {
    "photo": "Hill city hotel.webp"
  },
  {
    "photo": "Hill darksky.webp"
  },
  {
    "photo": "Hill inside.webp"
  },
  {
    "photo": "Hill sky pink.webp"
  },
  {
    "photo": "Hill sky.webp"
  },
  {
    "photo": "Hill top.webp"
  },
  {
    "photo": "Hill vintage.webp"
  },
  {
    "photo": "Himalay.webp"
  },
  {
    "photo": "Hongkong.webp"
  },
  {
    "photo": "Hot flower.webp"
  },
  {
    "photo": "Houses of parliament.webp"
  },
  {
    "photo": "Inside colors.webp"
  },
  {
    "photo": "Interial.webp"
  },
  {
    "photo": "Isa khan's tomb.webp"
  },
  {
    "photo": "Jantar mantar.webp"
  },
  {
    "photo": "Jasper.webp"
  },
  {
    "photo": "Jelifish.webp"
  },
  {
    "photo": "Jodhpur.webp"
  },
  {
    "photo": "Kerala.webp"
  },
  {
    "photo": "Laugh.webp"
  },
  {
    "photo": "Lava wallpaper.webp"
  },
  {
    "photo": "Lavender.webp"
  },
  {
    "photo": "Lend tree.webp"
  },
  {
    "photo": "Light river.webp"
  },
  {
    "photo": "Lilac.webp"
  },
  {
    "photo": "Line city.webp"
  },
  {
    "photo": "Lollipop.webp"
  },
  {
    "photo": "London beach.webp"
  },
  {
    "photo": "London time.webp"
  },
  {
    "photo": "Lottas flower.webp"
  },
  {
    "photo": "Lovely moments.webp"
  },
  {
    "photo": "Luxuria hotel.webp"
  },
  {
    "photo": "Luxury building.webp"
  },
  {
    "photo": "Luxury house.webp"
  },
  {
    "photo": "Mahal.webp"
  },
  {
    "photo": "Masroom.webp"
  },
  {
    "photo": "Men center.webp"
  },
  {
    "photo": "Mixed forests.webp"
  },
  {
    "photo": "Moon blue.webp"
  },
  {
    "photo": "Moon wallpaper hd.webp"
  },
  {
    "photo": "Motiovation.webp"
  },
  {
    "photo": "Moulin rouge.webp"
  },
  {
    "photo": "Mountain city.webp"
  },
  {
    "photo": "Mountain rocks.webp"
  },
  {
    "photo": "Mountain.webp"
  },
  {
    "photo": "Multicolored.webp"
  },
  {
    "photo": "Music.webp"
  },
  {
    "photo": "Mute swan.webp"
  },
  {
    "photo": "Nature tree.webp"
  },
  {
    "photo": "Neon light signs.webp"
  },
  {
    "photo": "Neon style.webp"
  },
  {
    "photo": "Neon women.webp"
  },
  {
    "photo": "Nepal.webp"
  },
  {
    "photo": "New Aesthetic.webp"
  },
  {
    "photo": "New year wishes.webp"
  },
  {
    "photo": "New year.webp"
  },
  {
    "photo": "Night sky green screen.webp"
  },
  {
    "photo": "Northern lights.webp"
  },
  {
    "photo": "Northland hills.webp"
  },
  {
    "photo": "Old building.webp"
  },
  {
    "photo": "One tree.webp"
  },
  {
    "photo": "Osian.webp"
  },
  {
    "photo": "Paan.webp"
  },
  {
    "photo": "Panda sad.webp"
  },
  {
    "photo": "Para pintar.webp"
  },
  {
    "photo": "Peak night sky.webp"
  },
  {
    "photo": "Perfect moment.webp"
  },
  {
    "photo": "Pink flower hd.webp"
  },
  {
    "photo": "Pinky flower.webp"
  },
  {
    "photo": "Pizza garlic bread.webp"
  },
  {
    "photo": "Plants.webp"
  },
  {
    "photo": "Rain flower drop.webp"
  },
  {
    "photo": "Rain flower.webp"
  },
  {
    "photo": "Red black hill.webp"
  },
  {
    "photo": "Red bus.webp"
  },
  {
    "photo": "Red drop.webp"
  },
  {
    "photo": "Red sky at morning.webp"
  },
  {
    "photo": "Rembow.webp"
  },
  {
    "photo": "River tent fire.webp"
  },
  {
    "photo": "Rock.webp"
  },
  {
    "photo": "Roma.webp"
  },
  {
    "photo": "Rose with drop.webp"
  },
  {
    "photo": "Sad men.webp"
  },
  {
    "photo": "Sahara.webp"
  },
  {
    "photo": "San francisco.webp"
  },
  {
    "photo": "Singal tree.webp"
  },
  {
    "photo": "Snow hard.webp"
  },
  {
    "photo": "Snow hill hd.webp"
  },
  {
    "photo": "Snow hill station.webp"
  },
  {
    "photo": "Snow sky hills.webp"
  },
  {
    "photo": "Snow view point.webp"
  },
  {
    "photo": "Snow with flowers.webp"
  },
  {
    "photo": "Snow.webp"
  },
  {
    "photo": "Space needle.webp"
  },
  {
    "photo": "Spark fly blue pink.webp"
  },
  {
    "photo": "Spring fever.webp"
  },
  {
    "photo": "Spring.webp"
  },
  {
    "photo": "Star flying.webp"
  },
  {
    "photo": "Step to beach.webp"
  },
  {
    "photo": "Street bright.webp"
  },
  {
    "photo": "Street car.webp"
  },
  {
    "photo": "Street light.webp"
  },
  {
    "photo": "Street.webp"
  },
  {
    "photo": "Subarray wall.webp"
  },
  {
    "photo": "Summer.webp"
  },
  {
    "photo": "Summit.webp"
  },
  {
    "photo": "Sun & hills.webp"
  },
  {
    "photo": "Sun river.webp"
  },
  {
    "photo": "Sunrise.webp"
  },
  {
    "photo": "Sunset horse.webp"
  },
  {
    "photo": "Sunset men.webp"
  },
  {
    "photo": "Sunset nature.webp"
  },
  {
    "photo": "Sunset river.webp"
  },
  {
    "photo": "Sunset side.webp"
  },
  {
    "photo": "Suryamukhi flower.webp"
  },
  {
    "photo": "Switzerland.webp"
  },
  {
    "photo": "Swizerlend sunset.webp"
  },
  {
    "photo": "Taj mahel.webp"
  },
  {
    "photo": "Tea.webp"
  },
  {
    "photo": "Temperate broadleaf.webp"
  },
  {
    "photo": "Temple.webp"
  },
  {
    "photo": "Terrace.webp"
  },
  {
    "photo": "Thor.webp"
  },
  {
    "photo": "Tourist attraction.webp"
  },
  {
    "photo": "Tower bridge.webp"
  },
  {
    "photo": "Travel influencers.webp"
  },
  {
    "photo": "Tree sunset.webp"
  },
  {
    "photo": "Tree with sky pink.webp"
  },
  {
    "photo": "Tulsi.webp"
  },
  {
    "photo": "Two sunflower.webp"
  },
  {
    "photo": "Valentines.webp"
  },
  {
    "photo": "Vertical.webp"
  },
  {
    "photo": "Vintage building.webp"
  },
  {
    "photo": "Vintage city.webp"
  },
  {
    "photo": "Vintage yellow.webp"
  },
  {
    "photo": "Wall art.webp"
  },
  {
    "photo": "Water balls.webp"
  },
  {
    "photo": "Water flowers.webp"
  },
  {
    "photo": "Waterfall blue.webp"
  },
  {
    "photo": "Waterfall dark.webp"
  },
  {
    "photo": "Waterfall forest.webp"
  },
  {
    "photo": "Waves.webp"
  },
  {
    "photo": "White cat.webp"
  },
  {
    "photo": "White flowers.webp"
  },
  {
    "photo": "White lily.webp"
  },
  {
    "photo": "Wind tower.webp"
  },
  {
    "photo": "Wooden background hd.webp"
  },
  {
    "photo": "Wooden port.webp"
  },
  {
    "photo": "Yellow flowers.webp"
  },
  {
    "photo": "Yellow red.webp"
  },
  {
    "photo": "Yellow.webp"
  }
]